Workbook

Sheet Sheet1
A1: Cindy’s 2026 Fixed Income Insights
A2: 月 | B2: 税前收入 | C2: 社保扣除 | D2: 公积金扣除 | E2: 个税扣除 | F2: 净收入 | I2: 支出预测
A3: 1 | B3: 18400 | C3: 1680 | D3: 1120 | E3: =VLOOKUP(A3,税额速算!I:N,6,0) -> 201 | F3: =B3-SUM(C3:E3) -> 15399 | I3: 房租 | J3: 2850
A4: 2 | B4: 18400 | C4: 1680 | D4: 1120 | E4: =VLOOKUP(A4,税额速算!I:N,6,0) -> 201 | F4: =B4-SUM(C4:E4) -> 15399 | I4: 餐饮 | J4: 2000
A5: 3 | B5: 18400 | C5: 1680 | D5: 1120 | E5: =VLOOKUP(A5,税额速算!I:N,6,0) -> 201 | F5: =B5-SUM(C5:E5) -> 15399 | I5: 交通 | J5: 500
A6: 4 | B6: 18400 | C6: 1680 | D6: 1120 | E6: =VLOOKUP(A6,税额速算!I:N,6,0) -> 201 | F6: =B6-SUM(C6:E6) -> 15399 | I6: 其他 | J6: 1000
A7: 5 | B7: 18400 | C7: 1680 | D7: 1120 | E7: =VLOOKUP(A7,税额速算!I:N,6,0) -> 201 | F7: =B7-SUM(C7:E7) -> 15399 | J7: =SUM(J3:J6) -> 6350
A8: 6 | B8: 18400 | C8: 1680 | D8: 1120 | E8: =VLOOKUP(A8,税额速算!I:N,6,0) -> 495 | F8: =B8-SUM(C8:E8) -> 15105 | I8: 年化支出 | J8: =J7*12 -> 76200
A9: 7 | B9: 18400 | C9: 1680 | D9: 1120 | E9: =VLOOKUP(A9,税额速算!I:N,6,0) -> 670 | F9: =B9-SUM(C9:E9) -> 14930
A10: 8 | B10: 18400 | C10: 1680 | D10: 1120 | E10: =VLOOKUP(A10,税额速算!I:N,6,0) -> 670 | F10: =B10-SUM(C10:E10) -> 14930
A11: 9 | B11: 18400 | C11: 1680 | D11: 1120 | E11: =VLOOKUP(A11,税额速算!I:N,6,0) -> 670 | F11: =B11-SUM(C11:E11) -> 14930
A12: 10 | B12: 18400 | C12: 1680 | D12: 1120 | E12: =VLOOKUP(A12,税额速算!I:N,6,0) -> 670 | F12: =B12-SUM(C12:E12) -> 14930
A13: 11 | B13: 18400 | C13: 1680 | D13: 1120 | E13: =VLOOKUP(A13,税额速算!I:N,6,0) -> 670 | F13: =B13-SUM(C13:E13) -> 14930
A14: 12 | B14: 18400 | C14: 1680 | D14: 1120 | E14: =VLOOKUP(A14,税额速算!I:N,6,0) -> 670 | F14: =B14-SUM(C14:E14) -> 14930
A15: 项目奖金 | B15: 18400 | E15: =B15*3%-0 -> 552 | F15: =B15-SUM(C15:E15) -> 17848 | K15: TOTAL ANNUAL GROSS | L15: =B16 -> 239200
A16: 全年 | B16: =SUM(B3:B15) -> 239200 | C16: =SUM(C3:C15) -> 20160 | D16: =SUM(D3:D15) -> 13440 | E16: =SUM(E3:E15) -> 6072 | F16: =SUM(F3:F15) -> 199528 | K16: TOTAL ANNUAL NET | L16: =F16 -> 199528
K17: NET RATIO | L17: =L16/L15 -> 0.83414716
K21: ANNUAL SAVINGS FORECAST | L21: =L16-J8 -> 123328
K22: 净储蓄率 | L22: =L21/L16 -> 0.61809871
L25: =L21/L15 -> 0.51558528

Sheet 税额速算
F1: 固定项目 | G1: 金额 | I1: 月份 | J1: 累计应纳税所得 | K1: 税率 | L1: 速算扣除数 | M1: 累计应缴个税 | N1: 当月应缴个税
A2: 累计预扣预缴应纳税所得额 | B2: 税率（%） | C2: 速算扣除数 | F2: 税前收入 | G2: 16000 | I2: 1 | J2: =G$7*I2 -> 6700 | K2: {=_xlfn.IFS(J2<=36000,3%,AND(J2>36000,J2<=144000),10%,J2>=144000,20%)} -> 0.03 | L2: {=_xlfn.IFS(J2<=36000,0,AND(J2>36000,J2<=144000),2520,J2>=144000,16920)} -> 0 | M2: =J2*K2-L2 -> 201 | N2: =M2 -> 201
A3: 不超过 36000 元的部分 | B3: 3 | C3: 0 | F3: 社保扣除 | G3: 1680 | I3: 2 | J3: =G$7*I3 -> 13400 | K3: {=_xlfn.IFS(J3<=36000,3%,AND(J3>36000,J3<=144000),10%,J3>=144000,20%)} -> 0.03 | L3: {=_xlfn.IFS(J3<=36000,0,AND(J3>36000,J3<=144000),2520,J3>=144000,16920)} -> 0 | M3: =J3*K3-L3 -> 402 | N3: =M3-M2 -> 201
A4: 超过 36000 元至 144000 元的部分 | B4: 10 | C4: 2520 | F4: 公积金扣除 | G4: 1120 | I4: 3 | J4: =G$7*I4 -> 20100 | K4: {=_xlfn.IFS(J4<=36000,3%,AND(J4>36000,J4<=144000),10%,J4>=144000,20%)} -> 0.03 | L4: {=_xlfn.IFS(J4<=36000,0,AND(J4>36000,J4<=144000),2520,J4>=144000,16920)} -> 0 | M4: =J4*K4-L4 -> 603 | N4: =M4-M3 -> 201
A5: 超过 144000 元至 300000 元的部分 | B5: 20 | C5: 16920 | F5: 基本减除费用（起征点） | G5: 5000 | I5: 4 | J5: =G$7*I5 -> 26800 | K5: {=_xlfn.IFS(J5<=36000,3%,AND(J5>36000,J5<=144000),10%,J5>=144000,20%)} -> 0.03 | L5: {=_xlfn.IFS(J5<=36000,0,AND(J5>36000,J5<=144000),2520,J5>=144000,16920)} -> 0 | M5: =J5*K5-L5 -> 804 | N5: =M5-M4 -> 201
F6: 租房专项附加扣除 | G6: 1500 | I6: 5 | J6: =G$7*I6 -> 33500 | K6: {=_xlfn.IFS(J6<=36000,3%,AND(J6>36000,J6<=144000),10%,J6>=144000,20%)} -> 0.03 | L6: {=_xlfn.IFS(J6<=36000,0,AND(J6>36000,J6<=144000),2520,J6>=144000,16920)} -> 0 | M6: =J6*K6-L6 -> 1005 | N6: =M6-M5 -> 201
G7: =G2-SUM(G3:G6) -> 6700 | I7: 6 | J7: =G$7*I7 -> 40200 | K7: {=_xlfn.IFS(J7<=36000,3%,AND(J7>36000,J7<=144000),10%,J7>=144000,20%)} -> 0.1 | L7: {=_xlfn.IFS(J7<=36000,0,AND(J7>36000,J7<=144000),2520,J7>=144000,16920)} -> 2520 | M7: =J7*K7-L7 -> 1500 | N7: =M7-M6 -> 495
I8: 7 | J8: =G$7*I8 -> 46900 | K8: {=_xlfn.IFS(J8<=36000,3%,AND(J8>36000,J8<=144000),10%,J8>=144000,20%)} -> 0.1 | L8: {=_xlfn.IFS(J8<=36000,0,AND(J8>36000,J8<=144000),2520,J8>=144000,16920)} -> 2520 | M8: =J8*K8-L8 -> 2170 | N8: =M8-M7 -> 670
I9: 8 | J9: =G$7*I9 -> 53600 | K9: {=_xlfn.IFS(J9<=36000,3%,AND(J9>36000,J9<=144000),10%,J9>=144000,20%)} -> 0.1 | L9: {=_xlfn.IFS(J9<=36000,0,AND(J9>36000,J9<=144000),2520,J9>=144000,16920)} -> 2520 | M9: =J9*K9-L9 -> 2840 | N9: =M9-M8 -> 670
I10: 9 | J10: =G$7*I10 -> 60300 | K10: {=_xlfn.IFS(J10<=36000,3%,AND(J10>36000,J10<=144000),10%,J10>=144000,20%)} -> 0.1 | L10: {=_xlfn.IFS(J10<=36000,0,AND(J10>36000,J10<=144000),2520,J10>=144000,16920)} -> 2520 | M10: =J10*K10-L10 -> 3510 | N10: =M10-M9 -> 670
I11: 10 | J11: =G$7*I11 -> 67000 | K11: {=_xlfn.IFS(J11<=36000,3%,AND(J11>36000,J11<=144000),10%,J11>=144000,20%)} -> 0.1 | L11: {=_xlfn.IFS(J11<=36000,0,AND(J11>36000,J11<=144000),2520,J11>=144000,16920)} -> 2520 | M11: =J11*K11-L11 -> 4180 | N11: =M11-M10 -> 670
I12: 11 | J12: =G$7*I12 -> 73700 | K12: {=_xlfn.IFS(J12<=36000,3%,AND(J12>36000,J12<=144000),10%,J12>=144000,20%)} -> 0.1 | L12: {=_xlfn.IFS(J12<=36000,0,AND(J12>36000,J12<=144000),2520,J12>=144000,16920)} -> 2520 | M12: =J12*K12-L12 -> 4850 | N12: =M12-M11 -> 670
I13: 12 | J13: =G$7*I13 -> 80400 | K13: {=_xlfn.IFS(J13<=36000,3%,AND(J13>36000,J13<=144000),10%,J13>=144000,20%)} -> 0.1 | L13: {=_xlfn.IFS(J13<=36000,0,AND(J13>36000,J13<=144000),2520,J13>=144000,16920)} -> 2520 | M13: =J13*K13-L13 -> 5520 | N13: =M13-M12 -> 670
